timed_decorator/__init__.py
timed_decorator/builder.py
timed_decorator/nested_timed.py
timed_decorator/simple_timed.py
timed_decorator/utils.py
timed_decorator-1.6.1.dist-info/LICENSE
timed_decorator-1.6.1.dist-info/METADATA
timed_decorator-1.6.1.dist-info/WHEEL
timed_decorator-1.6.1.dist-info/top_level.txt
timed_decorator-1.6.1.dist-info/RECORD
