Metadata-Version: 2.2
Name: timed-decorator
Version: 1.6.1
Summary: A timing decorator for python functions.
Author-email: George Stoica <58839912+ancestor-mithril@users.noreply.github.com>
Maintainer-email: George Stoica <58839912+ancestor-mithril@users.noreply.github.com>
License: Copyright (c) 2024 George Stoica
Project-URL: Repository, https://github.com/ancestor-mithril/timed-decorator
Project-URL: Issues, https://github.com/ancestor-mithril/timed-decorator/issues
Keywords: timing
Classifier: Development Status :: 5 - Production/Stable
Classifier: Intended Audience :: Developers
Classifier: License :: OSI Approved :: MIT License
Classifier: Operating System :: OS Independent
Classifier: Programming Language :: Python :: 3
Requires-Python: >=3.7
License-File: LICENSE
Provides-Extra: dev
Requires-Dist: pytest; extra == "dev"
Requires-Dist: flake8; extra == "dev"
Requires-Dist: torch; extra == "dev"
